m3u_maker.py
m3u_maker-0.1.4.dist-info/LICENSE
m3u_maker-0.1.4.dist-info/METADATA
m3u_maker-0.1.4.dist-info/WHEEL
m3u_maker-0.1.4.dist-info/entry_points.txt
m3u_maker-0.1.4.dist-info/top_level.txt
m3u_maker-0.1.4.dist-info/RECORD
