Metadata-Version: 2.1
Name: m3u-maker
Version: 0.1.4
Summary: finds music files in directory and create a m3u playlist
Home-page: https://github.com/CastixGitHub/m3u_maker
Author: Castix
Author-email: castix@autistici.org
Project-URL: Bug Reports, https://github.com/CastixGitHub/m3u_maker/issues
Project-URL: Source, https://github.com/CastixGitHub/m3u_maker
Keywords: m3u m3u8 playlist
Classifier: Development Status :: 5 - Production/Stable
Classifier: Environment :: Console
Classifier: Intended Audience :: End Users/Desktop
Classifier: Topic :: Multimedia :: Sound/Audio
Classifier: License :: OSI Approved :: GNU General Public License v3 or later (GPLv3+)
Classifier: Programming Language :: Python :: 3
Classifier: Programming Language :: Python :: 3.6
Classifier: Programming Language :: Python :: 3.7
Classifier: Programming Language :: Python :: 3.8
Classifier: Programming Language :: Python :: 3.9
Classifier: Programming Language :: Python :: 3.10
Classifier: Programming Language :: Python :: 3.11
Classifier: Programming Language :: Python :: 3 :: Only
Requires-Python: >=3.6
License-File: LICENSE
Requires-Dist: unidecode
Provides-Extra: test
Requires-Dist: coverage ; extra == 'test'
Requires-Dist: pytest ; extra == 'test'
Requires-Dist: pytest-cov ; extra == 'test'
